source_greenhouse/__init__.py
source_greenhouse/components.py
source_greenhouse/manifest.yaml
source_greenhouse/run.py
source_greenhouse/source.py
airbyte_source_greenhouse-0.6.1.dist-info/METADATA
airbyte_source_greenhouse-0.6.1.dist-info/WHEEL
airbyte_source_greenhouse-0.6.1.dist-info/entry_points.txt
airbyte_source_greenhouse-0.6.1.dist-info/RECORD
